models/__init__.py
models/augmentations.py
models/data_preprocess.py
models/model.py
models/pretrainmodel.py
models/pretrainmodel_vision.py
models/utils.py
SaintGSE-0.5.1.dist-info/METADATA
SaintGSE-0.5.1.dist-info/WHEEL
SaintGSE-0.5.1.dist-info/top_level.txt
SaintGSE-0.5.1.dist-info/RECORD
