Metadata-Version: 2.1
Name: SaintGSE
Version: 0.5.1
Summary: Package for distribution
Home-page: https://github.com/MSjeon27/SaintGSE
Author: msjeon27
Author-email: msjeon27@naver.com
License: UNKNOWN
Keywords: SAINTGSE,SaintGSE
Platform: UNKNOWN
Classifier: Programming Language :: Python :: 3
Classifier: License :: OSI Approved :: Apache Software License
Classifier: Operating System :: OS Independent
Requires-Python: >=3.8
Requires-Dist: torch
Requires-Dist: pandas
Requires-Dist: numpy
Requires-Dist: sklearn
